{
  "colors": {
    "primary-light": {
      "$type": "color",
      "$value": "{custom colors.lavender.600}"
    },
    "primary-dark": {
      "$type": "color",
      "$value": "{tailwind colors.zinc.50}"
    },
    "accent-light": {
      "$type": "color",
      "$value": "{custom colors.lavender.50}"
    },
    "accent-foreground-dark": {
      "$type": "color",
      "$value": "{tailwind colors.zinc.50}"
    },
    "background-light": {
      "$type": "color",
      "$value": "{tailwind colors.base.white}"
    },
    "background-dark": {
      "$type": "color",
      "$value": "{tailwind colors.zinc.950}"
    },
    "border-light": {
      "$type": "color",
      "$value": "{tailwind colors.zinc.200}"
    },
    "border-dark": {
      "$type": "color",
      "$value": "{tailwind colors.zinc.600}"
    },
    "card-light": {
      "$type": "color",
      "$value": "{tailwind colors.base.white}"
    },
    "card-dark": {
      "$type": "color",
      "$value": "{tailwind colors.zinc.950}"
    },
    "accent-dark": {
      "$type": "color",
      "$value": "{tailwind colors.zinc.800}"
    },
    "card-foreground-light": {
      "$type": "color",
      "$value": "{tailwind colors.zinc.950}"
    },
    "card-foreground-dark": {
      "$type": "color",
      "$value": "{tailwind colors.zinc.50}"
    },
    "destructive-light": {
      "$type": "color",
      "$value": "{tailwind colors.red.600}"
    },
    "destructive-dark": {
      "$type": "color",
      "$value": "{tailwind colors.red.900}"
    },
    "destructive-foreground-light": {
      "$type": "color",
      "$value": "{tailwind colors.red.50}"
    },
    "destructive-foreground-dark": {
      "$type": "color",
      "$value": "{tailwind colors.red.50}"
    },
    "accent-foreground-light": {
      "$type": "color",
      "$value": "{colors.primary-light}"
    },
    "foreground-light": {
      "$type": "color",
      "$value": "{tailwind colors.zinc.900}"
    },
    "foreground-dark": {
      "$type": "color",
      "$value": "{tailwind colors.zinc.50}"
    },
    "input-light": {
      "$type": "color",
      "$value": "{tailwind colors.zinc.200}"
    },
    "input-dark": {
      "$type": "color",
      "$value": "{tailwind colors.zinc.800}"
    },
    "muted-light": {
      "$type": "color",
      "$value": "{tailwind colors.zinc.100}"
    },
    "muted-dark": {
      "$type": "color",
      "$value": "{tailwind colors.zinc.800}"
    },
    "popover-light": {
      "$type": "color",
      "$value": "{tailwind colors.base.white}"
    },
    "popover-dark": {
      "$type": "color",
      "$value": "{tailwind colors.zinc.950}"
    },
    "popover-foreground-light": {
      "$type": "color",
      "$value": "{tailwind colors.zinc.950}"
    },
    "popover-foreground-dark": {
      "$type": "color",
      "$value": "{tailwind colors.zinc.50}"
    },
    "primary-foreground-light": {
      "$type": "color",
      "$value": "{tailwind colors.zinc.50}"
    },
    "primary-foreground-dark": {
      "$type": "color",
      "$value": "{tailwind colors.zinc.900}"
    },
    "ring-light": {
      "$type": "color",
      "$value": "{tailwind colors.zinc.900}"
    },
    "ring-dark": {
      "$type": "color",
      "$value": "{tailwind colors.zinc.300}"
    },
    "secondary-light": {
      "$type": "color",
      "$value": "{tailwind colors.zinc.50}"
    },
    "secondary-dark": {
      "$type": "color",
      "$value": "{tailwind colors.zinc.800}"
    },
    "secondary-foreground-light": {
      "$type": "color",
      "$value": "{tailwind colors.zinc.900}"
    },
    "secondary-foreground-dark": {
      "$type": "color",
      "$value": "{tailwind colors.zinc.50}"
    },
    "muted-foreground-light": {
      "$type": "color",
      "$value": "{tailwind colors.zinc.400}"
    },
    "muted-foreground-dark": {
      "$type": "color",
      "$value": "{tailwind colors.zinc.500}"
    },
    "chart-1-light": {
      "$type": "color",
      "$value": "#2a9d90"
    },
    "chart-1-dark": {
      "$type": "color",
      "$value": "#2662d9"
    },
    "chart-2-light": {
      "$type": "color",
      "$value": "#e76e50"
    },
    "chart-2-dark": {
      "$type": "color",
      "$value": "#e23670"
    },
    "chart-3-light": {
      "$type": "color",
      "$value": "#274754"
    },
    "chart-3-dark": {
      "$type": "color",
      "$value": "#e88c30"
    },
    "chart-4-light": {
      "$type": "color",
      "$value": "#e8c468"
    },
    "chart-4-dark": {
      "$type": "color",
      "$value": "#af57db"
    },
    "chart-5-light": {
      "$type": "color",
      "$value": "#f4a462"
    },
    "chart-5-dark": {
      "$type": "color",
      "$value": "#2eb88a"
    },
    "sidebar-background-light": {
      "$type": "color",
      "$value": "{tailwind colors.zinc.50}"
    },
    "sidebar-background-dark": {
      "$type": "color",
      "$value": "{tailwind colors.zinc.900}"
    },
    "sidebar-foreground-light": {
      "$type": "color",
      "$value": "{tailwind colors.zinc.700}"
    },
    "sidebar-foreground-dark": {
      "$type": "color",
      "$value": "{tailwind colors.zinc.100}"
    },
    "sidebar-primary-light": {
      "$type": "color",
      "$value": "{tailwind colors.zinc.900}"
    },
    "sidebar-primary-dark": {
      "$type": "color",
      "$value": "{tailwind colors.blue.700}"
    },
    "sidebar-primary-foreground-light": {
      "$type": "color",
      "$value": "{tailwind colors.zinc.50}"
    },
    "sidebar-primary-foreground-dark": {
      "$type": "color",
      "$value": "{tailwind colors.base.white}"
    },
    "sidebar-accent-light": {
      "$type": "color",
      "$value": "{tailwind colors.zinc.100}"
    },
    "sidebar-accent-dark": {
      "$type": "color",
      "$value": "{tailwind colors.zinc.800}"
    },
    "sidebar-accent-foreground-light": {
      "$type": "color",
      "$value": "{tailwind colors.zinc.900}"
    },
    "sidebar-accent-foreground-dark": {
      "$type": "color",
      "$value": "{tailwind colors.zinc.100}"
    },
    "sidebar-border-light": {
      "$type": "color",
      "$value": "{tailwind colors.gray.200}"
    },
    "sidebar-border-dark": {
      "$type": "color",
      "$value": "{tailwind colors.zinc.800}"
    },
    "sidebar-ring-light": {
      "$type": "color",
      "$value": "{tailwind colors.zinc.400}"
    },
    "sidebar-ring-dark": {
      "$type": "color",
      "$value": "{tailwind colors.zinc.300}"
    },
    "radiocard-secondaryunchecked-light": {
      "$type": "color",
      "$value": "{tailwind colors.red.700}"
    },
    "radiocard-secondaryunchecked-dark": {
      "$type": "color",
      "$value": "{tailwind colors.red.700}"
    },
    "radiocard-secondarychecked-light": {
      "$type": "color",
      "$value": "{tailwind colors.red.700}"
    },
    "radiocard-secondarychecked-dark": {
      "$type": "color",
      "$value": "{tailwind colors.red.700}"
    },
    "button-accent-light": {
      "$type": "color",
      "$value": "{tailwind colors.zinc.900}"
    },
    "button-accent-dark": {
      "$type": "color",
      "$value": "{tailwind colors.zinc.100}"
    }
  },
  "typography": {
    "font family": {
      "font-sans": {
        "$type": "text",
        "$value": "Poppins"
      },
      "font-serif": {
        "$type": "text",
        "$value": "Georgia"
      },
      "font-mono": {
        "$type": "text",
        "$value": "Menlo"
      },
      "font-sans-alt": {
        "$type": "text",
        "$value": "Area Variable"
      }
    },
    "typography components": {
      "h1": {
        "font-family": {
          "$type": "text",
          "$value": "{typography.font family.font-sans-alt}"
        },
        "font-size": {
          "$type": "number",
          "$value": "{font.size.text-4xl}"
        },
        "line-height": {
          "$type": "number",
          "$value": "{font.line-height.leading-10}"
        },
        "font-weight": {
          "$type": "number",
          "$value": "{font.weight.semibold}"
        },
        "letter-spacing": {
          "$type": "number",
          "$value": "{font.letter-spacing.tighter}"
        },
        "font-size-lg": {
          "$type": "number",
          "$value": "{font.size.text-5xl}"
        }
      },
      "h2": {
        "font-family": {
          "$type": "text",
          "$value": "{typography.font family.font-sans-alt}"
        },
        "font-size": {
          "$type": "number",
          "$value": "{font.size.text-3xl}"
        },
        "line-height": {
          "$type": "number",
          "$value": "{font.line-height.leading-9}"
        },
        "font-weight": {
          "$type": "number",
          "$value": "{font.weight.semibold}"
        },
        "letter-spacing": {
          "$type": "number",
          "$value": "{font.letter-spacing.tight}"
        }
      },
      "h3": {
        "font-family": {
          "$type": "text",
          "$value": "{typography.font family.font-sans-alt}"
        },
        "font-size": {
          "$type": "number",
          "$value": "{font.size.text-2xl}"
        },
        "line-height": {
          "$type": "number",
          "$value": "{font.line-height.leading-8}"
        },
        "font-weight": {
          "$type": "number",
          "$value": "{font.weight.semibold}"
        },
        "letter-spacing": {
          "$type": "number",
          "$value": "{font.letter-spacing.normal}"
        }
      },
      "h4": {
        "font-family": {
          "$type": "text",
          "$value": "{typography.font family.font-sans-alt}"
        },
        "font-size": {
          "$type": "number",
          "$value": "{font.size.text-xl}"
        },
        "line-height": {
          "$type": "number",
          "$value": "{font.line-height.leading-7}"
        },
        "font-weight": {
          "$type": "number",
          "$value": "{font.weight.semibold}"
        },
        "letter-spacing": {
          "$type": "number",
          "$value": "{font.letter-spacing.normal}"
        }
      },
      "p": {
        "font-family": {
          "$type": "text",
          "$value": "{typography.font family.font-sans}"
        },
        "font-size": {
          "$type": "number",
          "$value": "{font.size.text-base}"
        },
        "line-height": {
          "$type": "number",
          "$value": "{font.line-height.leading-7}"
        },
        "font-weight": {
          "$type": "number",
          "$value": "{font.weight.normal}"
        },
        "letter-spacing": {
          "$type": "number",
          "$value": "{font.letter-spacing.normal}"
        }
      },
      "blockquote": {
        "font-family": {
          "$type": "text",
          "$value": "{typography.font family.font-sans}"
        },
        "font-style": {
          "$type": "text",
          "$value": "{font.style.italic}"
        },
        "font-size": {
          "$type": "number",
          "$value": "{font.size.text-base}"
        },
        "line-height": {
          "$type": "number",
          "$value": "{font.line-height.leading-6}"
        },
        "font-weight": {
          "$type": "number",
          "$value": "{font.weight.normal}"
        },
        "letter-spacing": {
          "$type": "number",
          "$value": "{font.letter-spacing.normal}"
        }
      },
      "list": {
        "font-family": {
          "$type": "text",
          "$value": "{typography.font family.font-sans}"
        },
        "font-size": {
          "$type": "number",
          "$value": "{font.size.text-base}"
        },
        "line-height": {
          "$type": "number",
          "$value": "{font.line-height.leading-7}"
        },
        "font-weight": {
          "$type": "number",
          "$value": "{font.weight.normal}"
        },
        "letter-spacing": {
          "$type": "number",
          "$value": "{font.letter-spacing.normal}"
        }
      },
      "inline code": {
        "font-family": {
          "$type": "text",
          "$value": "{typography.font family.font-mono}"
        },
        "font-size": {
          "$type": "number",
          "$value": "{font.size.text-sm}"
        },
        "line-height": {
          "$type": "number",
          "$value": "{font.line-height.leading-5}"
        },
        "font-weight": {
          "$type": "number",
          "$value": "{font.weight.semibold}"
        },
        "letter-spacing": {
          "$type": "number",
          "$value": "{font.letter-spacing.normal}"
        }
      },
      "lead": {
        "font-family": {
          "$type": "text",
          "$value": "{typography.font family.font-sans}"
        },
        "font-size": {
          "$type": "number",
          "$value": "{font.size.text-xl}"
        },
        "line-height": {
          "$type": "number",
          "$value": "{font.line-height.leading-7}"
        },
        "font-weight": {
          "$type": "number",
          "$value": "{font.weight.normal}"
        },
        "letter-spacing": {
          "$type": "number",
          "$value": "{font.letter-spacing.normal}"
        }
      },
      "large": {
        "font-family": {
          "$type": "text",
          "$value": "{typography.font family.font-sans}"
        },
        "font-size": {
          "$type": "number",
          "$value": "{font.size.text-lg}"
        },
        "line-height": {
          "$type": "number",
          "$value": "{font.line-height.leading-7}"
        },
        "font-weight": {
          "$type": "number",
          "$value": "{font.weight.semibold}"
        },
        "letter-spacing": {
          "$type": "number",
          "$value": "{font.letter-spacing.normal}"
        }
      },
      "small": {
        "font-family": {
          "$type": "text",
          "$value": "{typography.font family.font-sans}"
        },
        "font-size": {
          "$type": "number",
          "$value": "{font.size.text-sm}"
        },
        "line-height": {
          "$type": "number",
          "$value": "{font.size.text-sm}"
        },
        "font-weight": {
          "$type": "number",
          "$value": "{font.weight.medium}"
        },
        "letter-spacing": {
          "$type": "number",
          "$value": "{font.line-height.leading-4}"
        }
      },
      "table": {
        "font-family": {
          "$type": "text",
          "$value": "{typography.font family.font-sans}"
        },
        "font-size": {
          "$type": "number",
          "$value": "{font.size.text-base}"
        },
        "font-weight": {
          "$type": "number",
          "$value": "{font.weight.normal}"
        },
        "letter-spacing": {
          "$type": "number",
          "$value": "{font.letter-spacing.normal}"
        },
        "font-weight-bold": {
          "$type": "number",
          "$value": "{font.weight.bold}"
        }
      }
    },
    "base sizes": {
      "2x large": {
        "font-family": {
          "$type": "text",
          "$value": "{typography.font family.font-sans-alt}"
        },
        "font-size": {
          "$type": "number",
          "$value": "{font.size.text-2xl}"
        },
        "line-height": {
          "$type": "number",
          "$value": "{font.line-height.leading-8}"
        },
        "letter-spacing": {
          "$type": "number",
          "$value": -1
        }
      },
      "3x large": {
        "font-family": {
          "$type": "text",
          "$value": "{typography.font family.font-sans-alt}"
        },
        "font-size": {
          "$type": "number",
          "$value": "{font.size.text-3xl}"
        },
        "line-height": {
          "$type": "number",
          "$value": "{font.line-height.leading-9}"
        },
        "letter-spacing": {
          "$type": "number",
          "$value": -1.65
        }
      },
      "4x large": {
        "font-family": {
          "$type": "text",
          "$value": "{typography.font family.font-sans-alt}"
        },
        "font-size": {
          "$type": "number",
          "$value": "{font.size.text-4xl}"
        },
        "line-height": {
          "$type": "number",
          "$value": "{font.line-height.leading-10}"
        },
        "letter-spacing": {
          "$type": "number",
          "$value": -1.7
        }
      },
      "5x large": {
        "font-family": {
          "$type": "text",
          "$value": "{typography.font family.font-sans-alt}"
        },
        "font-size": {
          "$type": "number",
          "$value": "{font.size.text-5xl}"
        },
        "line-height": {
          "$type": "number",
          "$value": "{font.size.text-5xl}"
        },
        "letter-spacing": {
          "$type": "number",
          "$value": -2.4
        }
      },
      "base": {
        "font-size": {
          "$type": "number",
          "$value": "{font.size.text-base}"
        },
        "line-height": {
          "$type": "number",
          "$value": "{font.line-height.leading-6}"
        },
        "letter-spacing": {
          "$type": "number",
          "$value": "{font.letter-spacing.normal}"
        }
      },
      "small": {
        "font-size": {
          "$type": "number",
          "$value": "{font.size.text-sm}"
        },
        "line-height": {
          "$type": "number",
          "$value": "{font.line-height.leading-5}"
        },
        "letter-spacing": {
          "$type": "number",
          "$value": "{font.letter-spacing.normal}"
        }
      },
      "large": {
        "font-size": {
          "$type": "number",
          "$value": "{font.size.text-lg}"
        },
        "line-height": {
          "$type": "number",
          "$value": "{font.line-height.leading-7}"
        },
        "letter-spacing": {
          "$type": "number",
          "$value": "{font.letter-spacing.normal}"
        }
      },
      "extra small": {
        "font-size": {
          "$type": "number",
          "$value": "{font.size.text-xs}"
        },
        "line-height": {
          "$type": "number",
          "$value": "{font.line-height.leading-4}"
        },
        "letter-spacing": {
          "$type": "number",
          "$value": "{font.letter-spacing.normal}"
        }
      },
      "xlarge": {
        "font-size": {
          "$type": "number",
          "$value": "{font.size.text-xl}"
        },
        "line-height": {
          "$type": "number",
          "$value": "{font.line-height.leading-7}"
        },
        "letter-spacing": {
          "$type": "number",
          "$value": "{font.letter-spacing.normal}"
        }
      }
    }
  },
  "border radius": {
    "default": {
      "$type": "number",
      "$value": "{radius.rounded-xl}"
    },
    "sm": {
      "$type": "number",
      "$value": "{radius.rounded-lg}"
    },
    "lg": {
      "$type": "number",
      "$value": "{radius.rounded-3xl}"
    },
    "full": {
      "$type": "number",
      "$value": "{radius.rounded-full}"
    },
    "xl": {
      "$type": "number",
      "$value": "{radius.rounded-4xl}"
    },
    "md": {
      "$type": "number",
      "$value": "{radius.rounded-2xl}"
    }
  },
  "rainbow-ui": {
    "$type": "color",
    "$value": "linear-gradient(135deg, #cc99e7 0%, #977ad8 50%, #b771db 100%)",
    "$description": "buttons, badges. Kein Background!"
  },
  "shadow": {
    "sm": {
      "$type": "boxShadow",
      "$value": {
        "color": "#0000000a",
        "type": "dropShadow",
        "x": 0,
        "y": 1,
        "blur": 2,
        "spread": 0
      }
    },
    "base": {
      "$type": "boxShadow",
      "$value": [
        {
          "color": "#0000000a",
          "type": "dropShadow",
          "x": 0,
          "y": 1,
          "blur": 2,
          "spread": 0
        },
        {
          "color": "#00000008",
          "type": "dropShadow",
          "x": 1,
          "y": 1,
          "blur": 6,
          "spread": 0
        }
      ]
    },
    "md": {
      "$type": "boxShadow",
      "$value": [
        {
          "color": "#0000000f",
          "type": "dropShadow",
          "x": 0,
          "y": 4,
          "blur": 6,
          "spread": -1
        },
        {
          "color": "#0000000f",
          "type": "dropShadow",
          "x": 0,
          "y": 2,
          "blur": 15,
          "spread": -1
        }
      ]
    },
    "lg": {
      "$type": "boxShadow",
      "$value": [
        {
          "color": "#00000012",
          "type": "dropShadow",
          "x": 0,
          "y": 10,
          "blur": 17,
          "spread": -3
        },
        {
          "color": "#00000008",
          "type": "dropShadow",
          "x": 0,
          "y": 4,
          "blur": 40,
          "spread": -2
        }
      ]
    },
    "xl": {
      "$type": "boxShadow",
      "$value": [
        {
          "color": "#0000000d",
          "type": "dropShadow",
          "x": 0,
          "y": 20,
          "blur": 35,
          "spread": -5
        },
        {
          "color": "#0000000d",
          "type": "dropShadow",
          "x": 0,
          "y": 10,
          "blur": 50,
          "spread": -5
        }
      ]
    },
    "2xl": {
      "$type": "boxShadow",
      "$value": {
        "color": "#00000033",
        "type": "dropShadow",
        "x": 0,
        "y": 25,
        "blur": 43,
        "spread": -12
      }
    },
    "inner": {
      "$type": "boxShadow",
      "$value": {
        "color": "#0000000f",
        "type": "innerShadow",
        "x": 0,
        "y": 2,
        "blur": 4,
        "spread": 0
      }
    }
  },
  "fontFamilies": {
    "poppins": {
      "$type": "fontFamilies",
      "$value": "Poppins"
    },
    "area-variable": {
      "$type": "fontFamilies",
      "$value": "Area Variable"
    }
  },
  "lineHeights": {
    "0": {
      "$type": "lineHeights",
      "$value": "100%"
    },
    "1": {
      "$type": "lineHeights",
      "$value": "16"
    },
    "2": {
      "$type": "lineHeights",
      "$value": "20"
    },
    "3": {
      "$type": "lineHeights",
      "$value": "24"
    },
    "4": {
      "$type": "lineHeights",
      "$value": "28"
    },
    "5": {
      "$type": "lineHeights",
      "$value": "32"
    },
    "6": {
      "$type": "lineHeights",
      "$value": "36"
    },
    "7": {
      "$type": "lineHeights",
      "$value": "40"
    },
    "8": {
      "$type": "lineHeights",
      "$value": "48"
    }
  },
  "fontWeights": {
    "poppins-0": {
      "$type": "fontWeights",
      "$value": "Regular"
    },
    "poppins-1": {
      "$type": "fontWeights",
      "$value": "Medium"
    },
    "poppins-2": {
      "$type": "fontWeights",
      "$value": "Italic"
    },
    "area-variable-3": {
      "$type": "fontWeights",
      "$value": "Regular"
    },
    "area-variable-4": {
      "$type": "fontWeights",
      "$value": "SemiBold"
    },
    "area-variable-5": {
      "$type": "fontWeights",
      "$value": "Regular Italic"
    }
  },
  "fontSize": {
    "0": {
      "$type": "fontSizes",
      "$value": "12"
    },
    "1": {
      "$type": "fontSizes",
      "$value": "14"
    },
    "2": {
      "$type": "fontSizes",
      "$value": "16"
    },
    "3": {
      "$type": "fontSizes",
      "$value": "18"
    },
    "4": {
      "$type": "fontSizes",
      "$value": "20"
    },
    "5": {
      "$type": "fontSizes",
      "$value": "24"
    },
    "6": {
      "$type": "fontSizes",
      "$value": "30"
    },
    "7": {
      "$type": "fontSizes",
      "$value": "36"
    },
    "8": {
      "$type": "fontSizes",
      "$value": "48"
    }
  },
  "letterSpacing": {
    "0": {
      "$type": "letterSpacing",
      "$value": "-0.25"
    },
    "1": {
      "$type": "letterSpacing",
      "$value": "-1"
    },
    "2": {
      "$type": "letterSpacing",
      "$value": "-1.65"
    },
    "3": {
      "$type": "letterSpacing",
      "$value": "-1.7"
    },
    "4": {
      "$type": "letterSpacing",
      "$value": "-2.4"
    }
  },
  "paragraphSpacing": {
    "0": {
      "$type": "paragraphSpacing",
      "$value": "0"
    }
  },
  "text extra small": {
    "leading-none": {
      "regular": {
        "$type": "typography",
        "$value": {
          "fontFamily": "{fontFamilies.poppins}",
          "fontWeight": "{fontWeights.poppins-0}",
          "lineHeight": "{lineHeights.0}",
          "fontSize": "{fontSize.0}",
          "letterSpacing": "{letterSpacing.0}",
          "paragraphSpacing": "{paragraphSpacing.0}",
          "paragraphIndent": "{paragraphIndent.0}",
          "textCase": "{textCase.none}",
          "textDecoration": "{textDecoration.none}"
        }
      },
      "medium": {
        "$type": "typography",
        "$value": {
          "fontFamily": "{fontFamilies.poppins}",
          "fontWeight": "{fontWeights.poppins-1}",
          "lineHeight": "{lineHeights.0}",
          "fontSize": "{fontSize.0}",
          "letterSpacing": "{letterSpacing.0}",
          "paragraphSpacing": "{paragraphSpacing.0}",
          "paragraphIndent": "{paragraphIndent.0}",
          "textCase": "{textCase.none}",
          "textDecoration": "{textDecoration.none}"
        }
      },
      "semibold": {
        "$type": "typography",
        "$value": {
          "fontFamily": "{fontFamilies.poppins}",
          "fontWeight": "{fontWeights.poppins-1}",
          "lineHeight": "{lineHeights.0}",
          "fontSize": "{fontSize.0}",
          "letterSpacing": "{letterSpacing.0}",
          "paragraphSpacing": "{paragraphSpacing.0}",
          "paragraphIndent": "{paragraphIndent.0}",
          "textCase": "{textCase.none}",
          "textDecoration": "{textDecoration.none}"
        }
      },
      "bold": {
        "$type": "typography",
        "$value": {
          "fontFamily": "{fontFamilies.poppins}",
          "fontWeight": "{fontWeights.poppins-1}",
          "lineHeight": "{lineHeights.0}",
          "fontSize": "{fontSize.0}",
          "letterSpacing": "{letterSpacing.0}",
          "paragraphSpacing": "{paragraphSpacing.0}",
          "paragraphIndent": "{paragraphIndent.0}",
          "textCase": "{textCase.none}",
          "textDecoration": "{textDecoration.none}"
        }
      },
      "italic": {
        "$type": "typography",
        "$value": {
          "fontFamily": "{fontFamilies.poppins}",
          "fontWeight": "{fontWeights.poppins-2}",
          "lineHeight": "{lineHeights.0}",
          "fontSize": "{fontSize.0}",
          "letterSpacing": "{letterSpacing.0}",
          "paragraphSpacing": "{paragraphSpacing.0}",
          "paragraphIndent": "{paragraphIndent.0}",
          "textCase": "{textCase.none}",
          "textDecoration": "{textDecoration.none}"
        }
      },
      "underlined": {
        "$type": "typography",
        "$value": {
          "fontFamily": "{fontFamilies.poppins}",
          "fontWeight": "{fontWeights.poppins-0}",
          "lineHeight": "{lineHeights.0}",
          "fontSize": "{fontSize.0}",
          "letterSpacing": "{letterSpacing.0}",
          "paragraphSpacing": "{paragraphSpacing.0}",
          "paragraphIndent": "{paragraphIndent.0}",
          "textCase": "{textCase.none}",
          "textDecoration": "{textDecoration.underline}"
        }
      },
      "strikethrough": {
        "$type": "typography",
        "$value": {
          "fontFamily": "{fontFamilies.poppins}",
          "fontWeight": "{fontWeights.poppins-0}",
          "lineHeight": "{lineHeights.0}",
          "fontSize": "{fontSize.0}",
          "letterSpacing": "{letterSpacing.0}",
          "paragraphSpacing": "{paragraphSpacing.0}",
          "paragraphIndent": "{paragraphIndent.0}",
          "textCase": "{textCase.none}",
          "textDecoration": "{textDecoration.line-through}"
        }
      }
    },
    "leading-normal": {
      "regular": {
        "$type": "typography",
        "$value": {
          "fontFamily": "{fontFamilies.poppins}",
          "fontWeight": "{fontWeights.poppins-0}",
          "lineHeight": "{lineHeights.1}",
          "fontSize": "{fontSize.0}",
          "letterSpacing": "{letterSpacing.0}",
          "paragraphSpacing": "{paragraphSpacing.0}",
          "paragraphIndent": "{paragraphIndent.0}",
          "textCase": "{textCase.none}",
          "textDecoration": "{textDecoration.none}"
        }
      },
      "medium": {
        "$type": "typography",
        "$value": {
          "fontFamily": "{fontFamilies.poppins}",
          "fontWeight": "{fontWeights.poppins-1}",
          "lineHeight": "{lineHeights.1}",
          "fontSize": "{fontSize.0}",
          "letterSpacing": "{letterSpacing.0}",
          "paragraphSpacing": "{paragraphSpacing.0}",
          "paragraphIndent": "{paragraphIndent.0}",
          "textCase": "{textCase.none}",
          "textDecoration": "{textDecoration.none}"
        }
      },
      "semibold": {
        "$type": "typography",
        "$value": {
          "fontFamily": "{fontFamilies.poppins}",
          "fontWeight": "{fontWeights.poppins-1}",
          "lineHeight": "{lineHeights.1}",
          "fontSize": "{fontSize.0}",
          "letterSpacing": "{letterSpacing.0}",
          "paragraphSpacing": "{paragraphSpacing.0}",
          "paragraphIndent": "{paragraphIndent.0}",
          "textCase": "{textCase.none}",
          "textDecoration": "{textDecoration.none}"
        }
      },
      "bold": {
        "$type": "typography",
        "$value": {
          "fontFamily": "{fontFamilies.poppins}",
          "fontWeight": "{fontWeights.poppins-1}",
          "lineHeight": "{lineHeights.1}",
          "fontSize": "{fontSize.0}",
          "letterSpacing": "{letterSpacing.0}",
          "paragraphSpacing": "{paragraphSpacing.0}",
          "paragraphIndent": "{paragraphIndent.0}",
          "textCase": "{textCase.none}",
          "textDecoration": "{textDecoration.none}"
        }
      },
      "italic": {
        "$type": "typography",
        "$value": {
          "fontFamily": "{fontFamilies.poppins}",
          "fontWeight": "{fontWeights.poppins-2}",
          "lineHeight": "{lineHeights.1}",
          "fontSize": "{fontSize.0}",
          "letterSpacing": "{letterSpacing.0}",
          "paragraphSpacing": "{paragraphSpacing.0}",
          "paragraphIndent": "{paragraphIndent.0}",
          "textCase": "{textCase.none}",
          "textDecoration": "{textDecoration.none}"
        }
      },
      "underlined": {
        "$type": "typography",
        "$value": {
          "fontFamily": "{fontFamilies.poppins}",
          "fontWeight": "{fontWeights.poppins-0}",
          "lineHeight": "{lineHeights.1}",
          "fontSize": "{fontSize.0}",
          "letterSpacing": "{letterSpacing.0}",
          "paragraphSpacing": "{paragraphSpacing.0}",
          "paragraphIndent": "{paragraphIndent.0}",
          "textCase": "{textCase.none}",
          "textDecoration": "{textDecoration.underline}"
        }
      },
      "strikethrough": {
        "$type": "typography",
        "$value": {
          "fontFamily": "{fontFamilies.poppins}",
          "fontWeight": "{fontWeights.poppins-0}",
          "lineHeight": "{lineHeights.1}",
          "fontSize": "{fontSize.0}",
          "letterSpacing": "{letterSpacing.0}",
          "paragraphSpacing": "{paragraphSpacing.0}",
          "paragraphIndent": "{paragraphIndent.0}",
          "textCase": "{textCase.none}",
          "textDecoration": "{textDecoration.line-through}"
        }
      }
    }
  },
  "text small": {
    "leading-normal": {
      "regular": {
        "$type": "typography",
        "$value": {
          "fontFamily": "{fontFamilies.poppins}",
          "fontWeight": "{fontWeights.poppins-0}",
          "lineHeight": "{lineHeights.2}",
          "fontSize": "{fontSize.1}",
          "letterSpacing": "{letterSpacing.0}",
          "paragraphSpacing": "{paragraphSpacing.0}",
          "paragraphIndent": "{paragraphIndent.0}",
          "textCase": "{textCase.none}",
          "textDecoration": "{textDecoration.none}"
        }
      },
      "medium": {
        "$type": "typography",
        "$value": {
          "fontFamily": "{fontFamilies.poppins}",
          "fontWeight": "{fontWeights.poppins-1}",
          "lineHeight": "{lineHeights.2}",
          "fontSize": "{fontSize.1}",
          "letterSpacing": "{letterSpacing.0}",
          "paragraphSpacing": "{paragraphSpacing.0}",
          "paragraphIndent": "{paragraphIndent.0}",
          "textCase": "{textCase.none}",
          "textDecoration": "{textDecoration.none}"
        }
      },
      "semibold": {
        "$type": "typography",
        "$value": {
          "fontFamily": "{fontFamilies.poppins}",
          "fontWeight": "{fontWeights.poppins-1}",
          "lineHeight": "{lineHeights.2}",
          "fontSize": "{fontSize.1}",
          "letterSpacing": "{letterSpacing.0}",
          "paragraphSpacing": "{paragraphSpacing.0}",
          "paragraphIndent": "{paragraphIndent.0}",
          "textCase": "{textCase.none}",
          "textDecoration": "{textDecoration.none}"
        }
      },
      "bold": {
        "$type": "typography",
        "$value": {
          "fontFamily": "{fontFamilies.poppins}",
          "fontWeight": "{fontWeights.poppins-1}",
          "lineHeight": "{lineHeights.2}",
          "fontSize": "{fontSize.1}",
          "letterSpacing": "{letterSpacing.0}",
          "paragraphSpacing": "{paragraphSpacing.0}",
          "paragraphIndent": "{paragraphIndent.0}",
          "textCase": "{textCase.none}",
          "textDecoration": "{textDecoration.none}"
        }
      },
      "italic": {
        "$type": "typography",
        "$value": {
          "fontFamily": "{fontFamilies.poppins}",
          "fontWeight": "{fontWeights.poppins-2}",
          "lineHeight": "{lineHeights.2}",
          "fontSize": "{fontSize.1}",
          "letterSpacing": "{letterSpacing.0}",
          "paragraphSpacing": "{paragraphSpacing.0}",
          "paragraphIndent": "{paragraphIndent.0}",
          "textCase": "{textCase.none}",
          "textDecoration": "{textDecoration.none}"
        }
      },
      "underlined": {
        "$type": "typography",
        "$value": {
          "fontFamily": "{fontFamilies.poppins}",
          "fontWeight": "{fontWeights.poppins-0}",
          "lineHeight": "{lineHeights.2}",
          "fontSize": "{fontSize.1}",
          "letterSpacing": "{letterSpacing.0}",
          "paragraphSpacing": "{paragraphSpacing.0}",
          "paragraphIndent": "{paragraphIndent.0}",
          "textCase": "{textCase.none}",
          "textDecoration": "{textDecoration.underline}"
        }
      },
      "strikethrough": {
        "$type": "typography",
        "$value": {
          "fontFamily": "{fontFamilies.poppins}",
          "fontWeight": "{fontWeights.poppins-0}",
          "lineHeight": "{lineHeights.2}",
          "fontSize": "{fontSize.1}",
          "letterSpacing": "{letterSpacing.0}",
          "paragraphSpacing": "{paragraphSpacing.0}",
          "paragraphIndent": "{paragraphIndent.0}",
          "textCase": "{textCase.none}",
          "textDecoration": "{textDecoration.line-through}"
        }
      },
      "underlined (medium)": {
        "$type": "typography",
        "$value": {
          "fontFamily": "{fontFamilies.poppins}",
          "fontWeight": "{fontWeights.poppins-1}",
          "lineHeight": "{lineHeights.2}",
          "fontSize": "{fontSize.1}",
          "letterSpacing": "{letterSpacing.0}",
          "paragraphSpacing": "{paragraphSpacing.0}",
          "paragraphIndent": "{paragraphIndent.0}",
          "textCase": "{textCase.none}",
          "textDecoration": "{textDecoration.underline}"
        }
      }
    },
    "leading-none": {
      "regular": {
        "$type": "typography",
        "$value": {
          "fontFamily": "{fontFamilies.poppins}",
          "fontWeight": "{fontWeights.poppins-0}",
          "lineHeight": "{lineHeights.0}",
          "fontSize": "{fontSize.1}",
          "letterSpacing": "{letterSpacing.0}",
          "paragraphSpacing": "{paragraphSpacing.0}",
          "paragraphIndent": "{paragraphIndent.0}",
          "textCase": "{textCase.none}",
          "textDecoration": "{textDecoration.none}"
        }
      },
      "medium": {
        "$type": "typography",
        "$value": {
          "fontFamily": "{fontFamilies.poppins}",
          "fontWeight": "{fontWeights.poppins-1}",
          "lineHeight": "{lineHeights.0}",
          "fontSize": "{fontSize.1}",
          "letterSpacing": "{letterSpacing.0}",
          "paragraphSpacing": "{paragraphSpacing.0}",
          "paragraphIndent": "{paragraphIndent.0}",
          "textCase": "{textCase.none}",
          "textDecoration": "{textDecoration.none}"
        }
      },
      "semibold": {
        "$type": "typography",
        "$value": {
          "fontFamily": "{fontFamilies.poppins}",
          "fontWeight": "{fontWeights.poppins-1}",
          "lineHeight": "{lineHeights.0}",
          "fontSize": "{fontSize.1}",
          "letterSpacing": "{letterSpacing.0}",
          "paragraphSpacing": "{paragraphSpacing.0}",
          "paragraphIndent": "{paragraphIndent.0}",
          "textCase": "{textCase.none}",
          "textDecoration": "{textDecoration.none}"
        }
      },
      "bold": {
        "$type": "typography",
        "$value": {
          "fontFamily": "{fontFamilies.poppins}",
          "fontWeight": "{fontWeights.poppins-1}",
          "lineHeight": "{lineHeights.0}",
          "fontSize": "{fontSize.1}",
          "letterSpacing": "{letterSpacing.0}",
          "paragraphSpacing": "{paragraphSpacing.0}",
          "paragraphIndent": "{paragraphIndent.0}",
          "textCase": "{textCase.none}",
          "textDecoration": "{textDecoration.none}"
        }
      },
      "italic": {
        "$type": "typography",
        "$value": {
          "fontFamily": "{fontFamilies.poppins}",
          "fontWeight": "{fontWeights.poppins-2}",
          "lineHeight": "{lineHeights.0}",
          "fontSize": "{fontSize.1}",
          "letterSpacing": "{letterSpacing.0}",
          "paragraphSpacing": "{paragraphSpacing.0}",
          "paragraphIndent": "{paragraphIndent.0}",
          "textCase": "{textCase.none}",
          "textDecoration": "{textDecoration.none}"
        }
      },
      "underlined": {
        "$type": "typography",
        "$value": {
          "fontFamily": "{fontFamilies.poppins}",
          "fontWeight": "{fontWeights.poppins-0}",
          "lineHeight": "{lineHeights.0}",
          "fontSize": "{fontSize.1}",
          "letterSpacing": "{letterSpacing.0}",
          "paragraphSpacing": "{paragraphSpacing.0}",
          "paragraphIndent": "{paragraphIndent.0}",
          "textCase": "{textCase.none}",
          "textDecoration": "{textDecoration.underline}"
        }
      },
      "strikethrough": {
        "$type": "typography",
        "$value": {
          "fontFamily": "{fontFamilies.poppins}",
          "fontWeight": "{fontWeights.poppins-0}",
          "lineHeight": "{lineHeights.0}",
          "fontSize": "{fontSize.1}",
          "letterSpacing": "{letterSpacing.0}",
          "paragraphSpacing": "{paragraphSpacing.0}",
          "paragraphIndent": "{paragraphIndent.0}",
          "textCase": "{textCase.none}",
          "textDecoration": "{textDecoration.line-through}"
        }
      }
    }
  },
  "text base": {
    "leading-normal": {
      "regular": {
        "$type": "typography",
        "$value": {
          "fontFamily": "{fontFamilies.poppins}",
          "fontWeight": "{fontWeights.poppins-0}",
          "lineHeight": "{lineHeights.3}",
          "fontSize": "{fontSize.2}",
          "letterSpacing": "{letterSpacing.0}",
          "paragraphSpacing": "{paragraphSpacing.0}",
          "paragraphIndent": "{paragraphIndent.0}",
          "textCase": "{textCase.none}",
          "textDecoration": "{textDecoration.none}"
        }
      },
      "medium": {
        "$type": "typography",
        "$value": {
          "fontFamily": "{fontFamilies.poppins}",
          "fontWeight": "{fontWeights.poppins-1}",
          "lineHeight": "{lineHeights.3}",
          "fontSize": "{fontSize.2}",
          "letterSpacing": "{letterSpacing.0}",
          "paragraphSpacing": "{paragraphSpacing.0}",
          "paragraphIndent": "{paragraphIndent.0}",
          "textCase": "{textCase.none}",
          "textDecoration": "{textDecoration.none}"
        }
      },
      "semibold": {
        "$type": "typography",
        "$value": {
          "fontFamily": "{fontFamilies.poppins}",
          "fontWeight": "{fontWeights.poppins-1}",
          "lineHeight": "{lineHeights.3}",
          "fontSize": "{fontSize.2}",
          "letterSpacing": "{letterSpacing.0}",
          "paragraphSpacing": "{paragraphSpacing.0}",
          "paragraphIndent": "{paragraphIndent.0}",
          "textCase": "{textCase.none}",
          "textDecoration": "{textDecoration.none}"
        }
      },
      "bold": {
        "$type": "typography",
        "$value": {
          "fontFamily": "{fontFamilies.poppins}",
          "fontWeight": "{fontWeights.poppins-1}",
          "lineHeight": "{lineHeights.3}",
          "fontSize": "{fontSize.2}",
          "letterSpacing": "{letterSpacing.0}",
          "paragraphSpacing": "{paragraphSpacing.0}",
          "paragraphIndent": "{paragraphIndent.0}",
          "textCase": "{textCase.none}",
          "textDecoration": "{textDecoration.none}"
        }
      },
      "italic": {
        "$type": "typography",
        "$value": {
          "fontFamily": "{fontFamilies.poppins}",
          "fontWeight": "{fontWeights.poppins-2}",
          "lineHeight": "{lineHeights.3}",
          "fontSize": "{fontSize.2}",
          "letterSpacing": "{letterSpacing.0}",
          "paragraphSpacing": "{paragraphSpacing.0}",
          "paragraphIndent": "{paragraphIndent.0}",
          "textCase": "{textCase.none}",
          "textDecoration": "{textDecoration.none}"
        }
      },
      "underlined": {
        "$type": "typography",
        "$value": {
          "fontFamily": "{fontFamilies.poppins}",
          "fontWeight": "{fontWeights.poppins-0}",
          "lineHeight": "{lineHeights.3}",
          "fontSize": "{fontSize.2}",
          "letterSpacing": "{letterSpacing.0}",
          "paragraphSpacing": "{paragraphSpacing.0}",
          "paragraphIndent": "{paragraphIndent.0}",
          "textCase": "{textCase.none}",
          "textDecoration": "{textDecoration.underline}"
        }
      },
      "strikethrough": {
        "$type": "typography",
        "$value": {
          "fontFamily": "{fontFamilies.poppins}",
          "fontWeight": "{fontWeights.poppins-0}",
          "lineHeight": "{lineHeights.3}",
          "fontSize": "{fontSize.2}",
          "letterSpacing": "{letterSpacing.0}",
          "paragraphSpacing": "{paragraphSpacing.0}",
          "paragraphIndent": "{paragraphIndent.0}",
          "textCase": "{textCase.none}",
          "textDecoration": "{textDecoration.line-through}"
        }
      },
      "underlined (medium)": {
        "$type": "typography",
        "$value": {
          "fontFamily": "{fontFamilies.poppins}",
          "fontWeight": "{fontWeights.poppins-1}",
          "lineHeight": "{lineHeights.3}",
          "fontSize": "{fontSize.2}",
          "letterSpacing": "{letterSpacing.0}",
          "paragraphSpacing": "{paragraphSpacing.0}",
          "paragraphIndent": "{paragraphIndent.0}",
          "textCase": "{textCase.none}",
          "textDecoration": "{textDecoration.underline}"
        }
      }
    },
    "leading-none": {
      "regular": {
        "$type": "typography",
        "$value": {
          "fontFamily": "{fontFamilies.poppins}",
          "fontWeight": "{fontWeights.poppins-0}",
          "lineHeight": "{lineHeights.0}",
          "fontSize": "{fontSize.2}",
          "letterSpacing": "{letterSpacing.0}",
          "paragraphSpacing": "{paragraphSpacing.0}",
          "paragraphIndent": "{paragraphIndent.0}",
          "textCase": "{textCase.none}",
          "textDecoration": "{textDecoration.none}"
        }
      },
      "medium": {
        "$type": "typography",
        "$value": {
          "fontFamily": "{fontFamilies.poppins}",
          "fontWeight": "{fontWeights.poppins-1}",
          "lineHeight": "{lineHeights.0}",
          "fontSize": "{fontSize.2}",
          "letterSpacing": "{letterSpacing.0}",
          "paragraphSpacing": "{paragraphSpacing.0}",
          "paragraphIndent": "{paragraphIndent.0}",
          "textCase": "{textCase.none}",
          "textDecoration": "{textDecoration.none}"
        }
      },
      "semibold": {
        "$type": "typography",
        "$value": {
          "fontFamily": "{fontFamilies.poppins}",
          "fontWeight": "{fontWeights.poppins-1}",
          "lineHeight": "{lineHeights.0}",
          "fontSize": "{fontSize.2}",
          "letterSpacing": "{letterSpacing.0}",
          "paragraphSpacing": "{paragraphSpacing.0}",
          "paragraphIndent": "{paragraphIndent.0}",
          "textCase": "{textCase.none}",
          "textDecoration": "{textDecoration.none}"
        }
      },
      "bold": {
        "$type": "typography",
        "$value": {
          "fontFamily": "{fontFamilies.poppins}",
          "fontWeight": "{fontWeights.poppins-1}",
          "lineHeight": "{lineHeights.0}",
          "fontSize": "{fontSize.2}",
          "letterSpacing": "{letterSpacing.0}",
          "paragraphSpacing": "{paragraphSpacing.0}",
          "paragraphIndent": "{paragraphIndent.0}",
          "textCase": "{textCase.none}",
          "textDecoration": "{textDecoration.none}"
        }
      },
      "italic": {
        "$type": "typography",
        "$value": {
          "fontFamily": "{fontFamilies.poppins}",
          "fontWeight": "{fontWeights.poppins-2}",
          "lineHeight": "{lineHeights.0}",
          "fontSize": "{fontSize.2}",
          "letterSpacing": "{letterSpacing.0}",
          "paragraphSpacing": "{paragraphSpacing.0}",
          "paragraphIndent": "{paragraphIndent.0}",
          "textCase": "{textCase.none}",
          "textDecoration": "{textDecoration.none}"
        }
      },
      "underlined": {
        "$type": "typography",
        "$value": {
          "fontFamily": "{fontFamilies.poppins}",
          "fontWeight": "{fontWeights.poppins-0}",
          "lineHeight": "{lineHeights.0}",
          "fontSize": "{fontSize.2}",
          "letterSpacing": "{letterSpacing.0}",
          "paragraphSpacing": "{paragraphSpacing.0}",
          "paragraphIndent": "{paragraphIndent.0}",
          "textCase": "{textCase.none}",
          "textDecoration": "{textDecoration.underline}"
        }
      },
      "strikethrough": {
        "$type": "typography",
        "$value": {
          "fontFamily": "{fontFamilies.poppins}",
          "fontWeight": "{fontWeights.poppins-0}",
          "lineHeight": "{lineHeights.0}",
          "fontSize": "{fontSize.2}",
          "letterSpacing": "{letterSpacing.0}",
          "paragraphSpacing": "{paragraphSpacing.0}",
          "paragraphIndent": "{paragraphIndent.0}",
          "textCase": "{textCase.none}",
          "textDecoration": "{textDecoration.line-through}"
        }
      }
    }
  },
  "text large": {
    "leading-normal": {
      "regular": {
        "$type": "typography",
        "$value": {
          "fontFamily": "{fontFamilies.poppins}",
          "fontWeight": "{fontWeights.poppins-0}",
          "lineHeight": "{lineHeights.4}",
          "fontSize": "{fontSize.3}",
          "letterSpacing": "{letterSpacing.0}",
          "paragraphSpacing": "{paragraphSpacing.0}",
          "paragraphIndent": "{paragraphIndent.0}",
          "textCase": "{textCase.none}",
          "textDecoration": "{textDecoration.none}"
        }
      },
      "medium": {
        "$type": "typography",
        "$value": {
          "fontFamily": "{fontFamilies.poppins}",
          "fontWeight": "{fontWeights.poppins-1}",
          "lineHeight": "{lineHeights.4}",
          "fontSize": "{fontSize.3}",
          "letterSpacing": "{letterSpacing.0}",
          "paragraphSpacing": "{paragraphSpacing.0}",
          "paragraphIndent": "{paragraphIndent.0}",
          "textCase": "{textCase.none}",
          "textDecoration": "{textDecoration.none}"
        }
      },
      "semibold": {
        "$type": "typography",
        "$value": {
          "fontFamily": "{fontFamilies.poppins}",
          "fontWeight": "{fontWeights.poppins-1}",
          "lineHeight": "{lineHeights.4}",
          "fontSize": "{fontSize.3}",
          "letterSpacing": "{letterSpacing.0}",
          "paragraphSpacing": "{paragraphSpacing.0}",
          "paragraphIndent": "{paragraphIndent.0}",
          "textCase": "{textCase.none}",
          "textDecoration": "{textDecoration.none}"
        }
      },
      "bold": {
        "$type": "typography",
        "$value": {
          "fontFamily": "{fontFamilies.poppins}",
          "fontWeight": "{fontWeights.poppins-1}",
          "lineHeight": "{lineHeights.4}",
          "fontSize": "{fontSize.3}",
          "letterSpacing": "{letterSpacing.0}",
          "paragraphSpacing": "{paragraphSpacing.0}",
          "paragraphIndent": "{paragraphIndent.0}",
          "textCase": "{textCase.none}",
          "textDecoration": "{textDecoration.none}"
        }
      },
      "italic": {
        "$type": "typography",
        "$value": {
          "fontFamily": "{fontFamilies.poppins}",
          "fontWeight": "{fontWeights.poppins-2}",
          "lineHeight": "{lineHeights.4}",
          "fontSize": "{fontSize.3}",
          "letterSpacing": "{letterSpacing.0}",
          "paragraphSpacing": "{paragraphSpacing.0}",
          "paragraphIndent": "{paragraphIndent.0}",
          "textCase": "{textCase.none}",
          "textDecoration": "{textDecoration.none}"
        }
      },
      "underlined": {
        "$type": "typography",
        "$value": {
          "fontFamily": "{fontFamilies.poppins}",
          "fontWeight": "{fontWeights.poppins-0}",
          "lineHeight": "{lineHeights.4}",
          "fontSize": "{fontSize.3}",
          "letterSpacing": "{letterSpacing.0}",
          "paragraphSpacing": "{paragraphSpacing.0}",
          "paragraphIndent": "{paragraphIndent.0}",
          "textCase": "{textCase.none}",
          "textDecoration": "{textDecoration.underline}"
        }
      },
      "strikethrough": {
        "$type": "typography",
        "$value": {
          "fontFamily": "{fontFamilies.poppins}",
          "fontWeight": "{fontWeights.poppins-0}",
          "lineHeight": "{lineHeights.4}",
          "fontSize": "{fontSize.3}",
          "letterSpacing": "{letterSpacing.0}",
          "paragraphSpacing": "{paragraphSpacing.0}",
          "paragraphIndent": "{paragraphIndent.0}",
          "textCase": "{textCase.none}",
          "textDecoration": "{textDecoration.line-through}"
        }
      }
    },
    "leading-none": {
      "regular": {
        "$type": "typography",
        "$value": {
          "fontFamily": "{fontFamilies.poppins}",
          "fontWeight": "{fontWeights.poppins-0}",
          "lineHeight": "{lineHeights.0}",
          "fontSize": "{fontSize.3}",
          "letterSpacing": "{letterSpacing.0}",
          "paragraphSpacing": "{paragraphSpacing.0}",
          "paragraphIndent": "{paragraphIndent.0}",
          "textCase": "{textCase.none}",
          "textDecoration": "{textDecoration.none}"
        }
      },
      "medium": {
        "$type": "typography",
        "$value": {
          "fontFamily": "{fontFamilies.poppins}",
          "fontWeight": "{fontWeights.poppins-1}",
          "lineHeight": "{lineHeights.0}",
          "fontSize": "{fontSize.3}",
          "letterSpacing": "{letterSpacing.0}",
          "paragraphSpacing": "{paragraphSpacing.0}",
          "paragraphIndent": "{paragraphIndent.0}",
          "textCase": "{textCase.none}",
          "textDecoration": "{textDecoration.none}"
        }
      },
      "semibold": {
        "$type": "typography",
        "$value": {
          "fontFamily": "{fontFamilies.poppins}",
          "fontWeight": "{fontWeights.poppins-1}",
          "lineHeight": "{lineHeights.0}",
          "fontSize": "{fontSize.3}",
          "letterSpacing": "{letterSpacing.0}",
          "paragraphSpacing": "{paragraphSpacing.0}",
          "paragraphIndent": "{paragraphIndent.0}",
          "textCase": "{textCase.none}",
          "textDecoration": "{textDecoration.none}"
        }
      },
      "bold": {
        "$type": "typography",
        "$value": {
          "fontFamily": "{fontFamilies.poppins}",
          "fontWeight": "{fontWeights.poppins-1}",
          "lineHeight": "{lineHeights.0}",
          "fontSize": "{fontSize.3}",
          "letterSpacing": "{letterSpacing.0}",
          "paragraphSpacing": "{paragraphSpacing.0}",
          "paragraphIndent": "{paragraphIndent.0}",
          "textCase": "{textCase.none}",
          "textDecoration": "{textDecoration.none}"
        }
      },
      "italic": {
        "$type": "typography",
        "$value": {
          "fontFamily": "{fontFamilies.poppins}",
          "fontWeight": "{fontWeights.poppins-2}",
          "lineHeight": "{lineHeights.0}",
          "fontSize": "{fontSize.3}",
          "letterSpacing": "{letterSpacing.0}",
          "paragraphSpacing": "{paragraphSpacing.0}",
          "paragraphIndent": "{paragraphIndent.0}",
          "textCase": "{textCase.none}",
          "textDecoration": "{textDecoration.none}"
        }
      },
      "underlined": {
        "$type": "typography",
        "$value": {
          "fontFamily": "{fontFamilies.poppins}",
          "fontWeight": "{fontWeights.poppins-0}",
          "lineHeight": "{lineHeights.0}",
          "fontSize": "{fontSize.3}",
          "letterSpacing": "{letterSpacing.0}",
          "paragraphSpacing": "{paragraphSpacing.0}",
          "paragraphIndent": "{paragraphIndent.0}",
          "textCase": "{textCase.none}",
          "textDecoration": "{textDecoration.underline}"
        }
      },
      "strikethrough": {
        "$type": "typography",
        "$value": {
          "fontFamily": "{fontFamilies.poppins}",
          "fontWeight": "{fontWeights.poppins-0}",
          "lineHeight": "{lineHeights.0}",
          "fontSize": "{fontSize.3}",
          "letterSpacing": "{letterSpacing.0}",
          "paragraphSpacing": "{paragraphSpacing.0}",
          "paragraphIndent": "{paragraphIndent.0}",
          "textCase": "{textCase.none}",
          "textDecoration": "{textDecoration.line-through}"
        }
      }
    }
  },
  "text extra large": {
    "leading-normal": {
      "regular": {
        "$type": "typography",
        "$value": {
          "fontFamily": "{fontFamilies.poppins}",
          "fontWeight": "{fontWeights.poppins-0}",
          "lineHeight": "{lineHeights.4}",
          "fontSize": "{fontSize.4}",
          "letterSpacing": "{letterSpacing.0}",
          "paragraphSpacing": "{paragraphSpacing.0}",
          "paragraphIndent": "{paragraphIndent.0}",
          "textCase": "{textCase.none}",
          "textDecoration": "{textDecoration.none}"
        }
      },
      "medium": {
        "$type": "typography",
        "$value": {
          "fontFamily": "{fontFamilies.poppins}",
          "fontWeight": "{fontWeights.poppins-1}",
          "lineHeight": "{lineHeights.4}",
          "fontSize": "{fontSize.4}",
          "letterSpacing": "{letterSpacing.0}",
          "paragraphSpacing": "{paragraphSpacing.0}",
          "paragraphIndent": "{paragraphIndent.0}",
          "textCase": "{textCase.none}",
          "textDecoration": "{textDecoration.none}"
        }
      },
      "semibold": {
        "$type": "typography",
        "$value": {
          "fontFamily": "{fontFamilies.poppins}",
          "fontWeight": "{fontWeights.poppins-1}",
          "lineHeight": "{lineHeights.4}",
          "fontSize": "{fontSize.4}",
          "letterSpacing": "{letterSpacing.0}",
          "paragraphSpacing": "{paragraphSpacing.0}",
          "paragraphIndent": "{paragraphIndent.0}",
          "textCase": "{textCase.none}",
          "textDecoration": "{textDecoration.none}"
        }
      },
      "bold": {
        "$type": "typography",
        "$value": {
          "fontFamily": "{fontFamilies.poppins}",
          "fontWeight": "{fontWeights.poppins-1}",
          "lineHeight": "{lineHeights.4}",
          "fontSize": "{fontSize.4}",
          "letterSpacing": "{letterSpacing.0}",
          "paragraphSpacing": "{paragraphSpacing.0}",
          "paragraphIndent": "{paragraphIndent.0}",
          "textCase": "{textCase.none}",
          "textDecoration": "{textDecoration.none}"
        }
      },
      "italic": {
        "$type": "typography",
        "$value": {
          "fontFamily": "{fontFamilies.poppins}",
          "fontWeight": "{fontWeights.poppins-2}",
          "lineHeight": "{lineHeights.4}",
          "fontSize": "{fontSize.4}",
          "letterSpacing": "{letterSpacing.0}",
          "paragraphSpacing": "{paragraphSpacing.0}",
          "paragraphIndent": "{paragraphIndent.0}",
          "textCase": "{textCase.none}",
          "textDecoration": "{textDecoration.none}"
        }
      },
      "underlined": {
        "$type": "typography",
        "$value": {
          "fontFamily": "{fontFamilies.poppins}",
          "fontWeight": "{fontWeights.poppins-0}",
          "lineHeight": "{lineHeights.4}",
          "fontSize": "{fontSize.4}",
          "letterSpacing": "{letterSpacing.0}",
          "paragraphSpacing": "{paragraphSpacing.0}",
          "paragraphIndent": "{paragraphIndent.0}",
          "textCase": "{textCase.none}",
          "textDecoration": "{textDecoration.underline}"
        }
      },
      "strikethrough": {
        "$type": "typography",
        "$value": {
          "fontFamily": "{fontFamilies.poppins}",
          "fontWeight": "{fontWeights.poppins-0}",
          "lineHeight": "{lineHeights.4}",
          "fontSize": "{fontSize.4}",
          "letterSpacing": "{letterSpacing.0}",
          "paragraphSpacing": "{paragraphSpacing.0}",
          "paragraphIndent": "{paragraphIndent.0}",
          "textCase": "{textCase.none}",
          "textDecoration": "{textDecoration.line-through}"
        }
      }
    },
    "leading-none": {
      "regular": {
        "$type": "typography",
        "$value": {
          "fontFamily": "{fontFamilies.poppins}",
          "fontWeight": "{fontWeights.poppins-0}",
          "lineHeight": "{lineHeights.0}",
          "fontSize": "{fontSize.4}",
          "letterSpacing": "{letterSpacing.0}",
          "paragraphSpacing": "{paragraphSpacing.0}",
          "paragraphIndent": "{paragraphIndent.0}",
          "textCase": "{textCase.none}",
          "textDecoration": "{textDecoration.none}"
        }
      },
      "medium": {
        "$type": "typography",
        "$value": {
          "fontFamily": "{fontFamilies.poppins}",
          "fontWeight": "{fontWeights.poppins-1}",
          "lineHeight": "{lineHeights.0}",
          "fontSize": "{fontSize.4}",
          "letterSpacing": "{letterSpacing.0}",
          "paragraphSpacing": "{paragraphSpacing.0}",
          "paragraphIndent": "{paragraphIndent.0}",
          "textCase": "{textCase.none}",
          "textDecoration": "{textDecoration.none}"
        }
      },
      "semibold": {
        "$type": "typography",
        "$value": {
          "fontFamily": "{fontFamilies.poppins}",
          "fontWeight": "{fontWeights.poppins-1}",
          "lineHeight": "{lineHeights.0}",
          "fontSize": "{fontSize.4}",
          "letterSpacing": "{letterSpacing.0}",
          "paragraphSpacing": "{paragraphSpacing.0}",
          "paragraphIndent": "{paragraphIndent.0}",
          "textCase": "{textCase.none}",
          "textDecoration": "{textDecoration.none}"
        }
      },
      "bold": {
        "$type": "typography",
        "$value": {
          "fontFamily": "{fontFamilies.poppins}",
          "fontWeight": "{fontWeights.poppins-1}",
          "lineHeight": "{lineHeights.0}",
          "fontSize": "{fontSize.4}",
          "letterSpacing": "{letterSpacing.0}",
          "paragraphSpacing": "{paragraphSpacing.0}",
          "paragraphIndent": "{paragraphIndent.0}",
          "textCase": "{textCase.none}",
          "textDecoration": "{textDecoration.none}"
        }
      },
      "italic": {
        "$type": "typography",
        "$value": {
          "fontFamily": "{fontFamilies.poppins}",
          "fontWeight": "{fontWeights.poppins-2}",
          "lineHeight": "{lineHeights.0}",
          "fontSize": "{fontSize.4}",
          "letterSpacing": "{letterSpacing.0}",
          "paragraphSpacing": "{paragraphSpacing.0}",
          "paragraphIndent": "{paragraphIndent.0}",
          "textCase": "{textCase.none}",
          "textDecoration": "{textDecoration.none}"
        }
      },
      "strikethrough": {
        "$type": "typography",
        "$value": {
          "fontFamily": "{fontFamilies.poppins}",
          "fontWeight": "{fontWeights.poppins-0}",
          "lineHeight": "{lineHeights.0}",
          "fontSize": "{fontSize.4}",
          "letterSpacing": "{letterSpacing.0}",
          "paragraphSpacing": "{paragraphSpacing.0}",
          "paragraphIndent": "{paragraphIndent.0}",
          "textCase": "{textCase.none}",
          "textDecoration": "{textDecoration.line-through}"
        }
      },
      "underlined": {
        "$type": "typography",
        "$value": {
          "fontFamily": "{fontFamilies.poppins}",
          "fontWeight": "{fontWeights.poppins-0}",
          "lineHeight": "{lineHeights.0}",
          "fontSize": "{fontSize.4}",
          "letterSpacing": "{letterSpacing.0}",
          "paragraphSpacing": "{paragraphSpacing.0}",
          "paragraphIndent": "{paragraphIndent.0}",
          "textCase": "{textCase.none}",
          "textDecoration": "{textDecoration.underline}"
        }
      }
    }
  },
  "text 2x large": {
    "leading-normal": {
      "regular": {
        "$type": "typography",
        "$value": {
          "fontFamily": "{fontFamilies.area-variable}",
          "fontWeight": "{fontWeights.area-variable-3}",
          "lineHeight": "{lineHeights.5}",
          "fontSize": "{fontSize.5}",
          "letterSpacing": "{letterSpacing.1}",
          "paragraphSpacing": "{paragraphSpacing.0}",
          "paragraphIndent": "{paragraphIndent.0}",
          "textCase": "{textCase.none}",
          "textDecoration": "{textDecoration.none}"
        }
      },
      "medium": {
        "$type": "typography",
        "$value": {
          "fontFamily": "{fontFamilies.area-variable}",
          "fontWeight": "{fontWeights.area-variable-3}",
          "lineHeight": "{lineHeights.5}",
          "fontSize": "{fontSize.5}",
          "letterSpacing": "{letterSpacing.1}",
          "paragraphSpacing": "{paragraphSpacing.0}",
          "paragraphIndent": "{paragraphIndent.0}",
          "textCase": "{textCase.none}",
          "textDecoration": "{textDecoration.none}"
        }
      },
      "semibold": {
        "$type": "typography",
        "$value": {
          "fontFamily": "{fontFamilies.area-variable}",
          "fontWeight": "{fontWeights.area-variable-4}",
          "lineHeight": "{lineHeights.5}",
          "fontSize": "{fontSize.5}",
          "letterSpacing": "{letterSpacing.1}",
          "paragraphSpacing": "{paragraphSpacing.0}",
          "paragraphIndent": "{paragraphIndent.0}",
          "textCase": "{textCase.none}",
          "textDecoration": "{textDecoration.none}"
        }
      },
      "bold": {
        "$type": "typography",
        "$value": {
          "fontFamily": "{fontFamilies.area-variable}",
          "fontWeight": "{fontWeights.area-variable-4}",
          "lineHeight": "{lineHeights.5}",
          "fontSize": "{fontSize.5}",
          "letterSpacing": "{letterSpacing.1}",
          "paragraphSpacing": "{paragraphSpacing.0}",
          "paragraphIndent": "{paragraphIndent.0}",
          "textCase": "{textCase.none}",
          "textDecoration": "{textDecoration.none}"
        }
      },
      "italic": {
        "$type": "typography",
        "$value": {
          "fontFamily": "{fontFamilies.area-variable}",
          "fontWeight": "{fontWeights.area-variable-5}",
          "lineHeight": "{lineHeights.5}",
          "fontSize": "{fontSize.5}",
          "letterSpacing": "{letterSpacing.1}",
          "paragraphSpacing": "{paragraphSpacing.0}",
          "paragraphIndent": "{paragraphIndent.0}",
          "textCase": "{textCase.none}",
          "textDecoration": "{textDecoration.none}"
        }
      },
      "underlined": {
        "$type": "typography",
        "$value": {
          "fontFamily": "{fontFamilies.area-variable}",
          "fontWeight": "{fontWeights.area-variable-3}",
          "lineHeight": "{lineHeights.5}",
          "fontSize": "{fontSize.5}",
          "letterSpacing": "{letterSpacing.1}",
          "paragraphSpacing": "{paragraphSpacing.0}",
          "paragraphIndent": "{paragraphIndent.0}",
          "textCase": "{textCase.none}",
          "textDecoration": "{textDecoration.underline}"
        }
      },
      "strikethrough": {
        "$type": "typography",
        "$value": {
          "fontFamily": "{fontFamilies.area-variable}",
          "fontWeight": "{fontWeights.area-variable-3}",
          "lineHeight": "{lineHeights.5}",
          "fontSize": "{fontSize.5}",
          "letterSpacing": "{letterSpacing.1}",
          "paragraphSpacing": "{paragraphSpacing.0}",
          "paragraphIndent": "{paragraphIndent.0}",
          "textCase": "{textCase.none}",
          "textDecoration": "{textDecoration.line-through}"
        }
      }
    },
    "leading-none": {
      "regular": {
        "$type": "typography",
        "$value": {
          "fontFamily": "{fontFamilies.area-variable}",
          "fontWeight": "{fontWeights.area-variable-3}",
          "lineHeight": "{lineHeights.0}",
          "fontSize": "{fontSize.5}",
          "letterSpacing": "{letterSpacing.1}",
          "paragraphSpacing": "{paragraphSpacing.0}",
          "paragraphIndent": "{paragraphIndent.0}",
          "textCase": "{textCase.none}",
          "textDecoration": "{textDecoration.none}"
        }
      },
      "medium": {
        "$type": "typography",
        "$value": {
          "fontFamily": "{fontFamilies.area-variable}",
          "fontWeight": "{fontWeights.area-variable-3}",
          "lineHeight": "{lineHeights.0}",
          "fontSize": "{fontSize.5}",
          "letterSpacing": "{letterSpacing.1}",
          "paragraphSpacing": "{paragraphSpacing.0}",
          "paragraphIndent": "{paragraphIndent.0}",
          "textCase": "{textCase.none}",
          "textDecoration": "{textDecoration.none}"
        }
      },
      "semibold": {
        "$type": "typography",
        "$value": {
          "fontFamily": "{fontFamilies.area-variable}",
          "fontWeight": "{fontWeights.area-variable-4}",
          "lineHeight": "{lineHeights.0}",
          "fontSize": "{fontSize.5}",
          "letterSpacing": "{letterSpacing.1}",
          "paragraphSpacing": "{paragraphSpacing.0}",
          "paragraphIndent": "{paragraphIndent.0}",
          "textCase": "{textCase.none}",
          "textDecoration": "{textDecoration.none}"
        }
      },
      "bold": {
        "$type": "typography",
        "$value": {
          "fontFamily": "{fontFamilies.area-variable}",
          "fontWeight": "{fontWeights.area-variable-4}",
          "lineHeight": "{lineHeights.0}",
          "fontSize": "{fontSize.5}",
          "letterSpacing": "{letterSpacing.1}",
          "paragraphSpacing": "{paragraphSpacing.0}",
          "paragraphIndent": "{paragraphIndent.0}",
          "textCase": "{textCase.none}",
          "textDecoration": "{textDecoration.none}"
        }
      },
      "italic": {
        "$type": "typography",
        "$value": {
          "fontFamily": "{fontFamilies.area-variable}",
          "fontWeight": "{fontWeights.area-variable-5}",
          "lineHeight": "{lineHeights.0}",
          "fontSize": "{fontSize.5}",
          "letterSpacing": "{letterSpacing.1}",
          "paragraphSpacing": "{paragraphSpacing.0}",
          "paragraphIndent": "{paragraphIndent.0}",
          "textCase": "{textCase.none}",
          "textDecoration": "{textDecoration.none}"
        }
      },
      "underlined": {
        "$type": "typography",
        "$value": {
          "fontFamily": "{fontFamilies.area-variable}",
          "fontWeight": "{fontWeights.area-variable-3}",
          "lineHeight": "{lineHeights.0}",
          "fontSize": "{fontSize.5}",
          "letterSpacing": "{letterSpacing.1}",
          "paragraphSpacing": "{paragraphSpacing.0}",
          "paragraphIndent": "{paragraphIndent.0}",
          "textCase": "{textCase.none}",
          "textDecoration": "{textDecoration.underline}"
        }
      },
      "strikethrough": {
        "$type": "typography",
        "$value": {
          "fontFamily": "{fontFamilies.area-variable}",
          "fontWeight": "{fontWeights.area-variable-3}",
          "lineHeight": "{lineHeights.0}",
          "fontSize": "{fontSize.5}",
          "letterSpacing": "{letterSpacing.1}",
          "paragraphSpacing": "{paragraphSpacing.0}",
          "paragraphIndent": "{paragraphIndent.0}",
          "textCase": "{textCase.none}",
          "textDecoration": "{textDecoration.line-through}"
        }
      }
    }
  },
  "text 3x large": {
    "leading-normal": {
      "regular": {
        "$type": "typography",
        "$value": {
          "fontFamily": "{fontFamilies.area-variable}",
          "fontWeight": "{fontWeights.area-variable-3}",
          "lineHeight": "{lineHeights.6}",
          "fontSize": "{fontSize.6}",
          "letterSpacing": "{letterSpacing.2}",
          "paragraphSpacing": "{paragraphSpacing.0}",
          "paragraphIndent": "{paragraphIndent.0}",
          "textCase": "{textCase.none}",
          "textDecoration": "{textDecoration.none}"
        }
      },
      "medium": {
        "$type": "typography",
        "$value": {
          "fontFamily": "{fontFamilies.area-variable}",
          "fontWeight": "{fontWeights.area-variable-3}",
          "lineHeight": "{lineHeights.6}",
          "fontSize": "{fontSize.6}",
          "letterSpacing": "{letterSpacing.2}",
          "paragraphSpacing": "{paragraphSpacing.0}",
          "paragraphIndent": "{paragraphIndent.0}",
          "textCase": "{textCase.none}",
          "textDecoration": "{textDecoration.none}"
        }
      },
      "semibold": {
        "$type": "typography",
        "$value": {
          "fontFamily": "{fontFamilies.area-variable}",
          "fontWeight": "{fontWeights.area-variable-4}",
          "lineHeight": "{lineHeights.6}",
          "fontSize": "{fontSize.6}",
          "letterSpacing": "{letterSpacing.2}",
          "paragraphSpacing": "{paragraphSpacing.0}",
          "paragraphIndent": "{paragraphIndent.0}",
          "textCase": "{textCase.none}",
          "textDecoration": "{textDecoration.none}"
        }
      },
      "bold": {
        "$type": "typography",
        "$value": {
          "fontFamily": "{fontFamilies.area-variable}",
          "fontWeight": "{fontWeights.area-variable-4}",
          "lineHeight": "{lineHeights.6}",
          "fontSize": "{fontSize.6}",
          "letterSpacing": "{letterSpacing.2}",
          "paragraphSpacing": "{paragraphSpacing.0}",
          "paragraphIndent": "{paragraphIndent.0}",
          "textCase": "{textCase.none}",
          "textDecoration": "{textDecoration.none}"
        }
      },
      "italic": {
        "$type": "typography",
        "$value": {
          "fontFamily": "{fontFamilies.area-variable}",
          "fontWeight": "{fontWeights.area-variable-5}",
          "lineHeight": "{lineHeights.6}",
          "fontSize": "{fontSize.6}",
          "letterSpacing": "{letterSpacing.2}",
          "paragraphSpacing": "{paragraphSpacing.0}",
          "paragraphIndent": "{paragraphIndent.0}",
          "textCase": "{textCase.none}",
          "textDecoration": "{textDecoration.none}"
        }
      },
      "underlined": {
        "$type": "typography",
        "$value": {
          "fontFamily": "{fontFamilies.area-variable}",
          "fontWeight": "{fontWeights.area-variable-3}",
          "lineHeight": "{lineHeights.6}",
          "fontSize": "{fontSize.6}",
          "letterSpacing": "{letterSpacing.2}",
          "paragraphSpacing": "{paragraphSpacing.0}",
          "paragraphIndent": "{paragraphIndent.0}",
          "textCase": "{textCase.none}",
          "textDecoration": "{textDecoration.underline}"
        }
      },
      "strikethrough": {
        "$type": "typography",
        "$value": {
          "fontFamily": "{fontFamilies.area-variable}",
          "fontWeight": "{fontWeights.area-variable-3}",
          "lineHeight": "{lineHeights.6}",
          "fontSize": "{fontSize.6}",
          "letterSpacing": "{letterSpacing.2}",
          "paragraphSpacing": "{paragraphSpacing.0}",
          "paragraphIndent": "{paragraphIndent.0}",
          "textCase": "{textCase.none}",
          "textDecoration": "{textDecoration.line-through}"
        }
      }
    },
    "leading-none": {
      "regular": {
        "$type": "typography",
        "$value": {
          "fontFamily": "{fontFamilies.area-variable}",
          "fontWeight": "{fontWeights.area-variable-3}",
          "lineHeight": "{lineHeights.0}",
          "fontSize": "{fontSize.6}",
          "letterSpacing": "{letterSpacing.2}",
          "paragraphSpacing": "{paragraphSpacing.0}",
          "paragraphIndent": "{paragraphIndent.0}",
          "textCase": "{textCase.none}",
          "textDecoration": "{textDecoration.none}"
        }
      },
      "medium": {
        "$type": "typography",
        "$value": {
          "fontFamily": "{fontFamilies.area-variable}",
          "fontWeight": "{fontWeights.area-variable-3}",
          "lineHeight": "{lineHeights.0}",
          "fontSize": "{fontSize.6}",
          "letterSpacing": "{letterSpacing.2}",
          "paragraphSpacing": "{paragraphSpacing.0}",
          "paragraphIndent": "{paragraphIndent.0}",
          "textCase": "{textCase.none}",
          "textDecoration": "{textDecoration.none}"
        }
      },
      "semibold": {
        "$type": "typography",
        "$value": {
          "fontFamily": "{fontFamilies.area-variable}",
          "fontWeight": "{fontWeights.area-variable-4}",
          "lineHeight": "{lineHeights.0}",
          "fontSize": "{fontSize.6}",
          "letterSpacing": "{letterSpacing.2}",
          "paragraphSpacing": "{paragraphSpacing.0}",
          "paragraphIndent": "{paragraphIndent.0}",
          "textCase": "{textCase.none}",
          "textDecoration": "{textDecoration.none}"
        }
      },
      "bold": {
        "$type": "typography",
        "$value": {
          "fontFamily": "{fontFamilies.area-variable}",
          "fontWeight": "{fontWeights.area-variable-4}",
          "lineHeight": "{lineHeights.0}",
          "fontSize": "{fontSize.6}",
          "letterSpacing": "{letterSpacing.2}",
          "paragraphSpacing": "{paragraphSpacing.0}",
          "paragraphIndent": "{paragraphIndent.0}",
          "textCase": "{textCase.none}",
          "textDecoration": "{textDecoration.none}"
        }
      },
      "italic": {
        "$type": "typography",
        "$value": {
          "fontFamily": "{fontFamilies.area-variable}",
          "fontWeight": "{fontWeights.area-variable-5}",
          "lineHeight": "{lineHeights.0}",
          "fontSize": "{fontSize.6}",
          "letterSpacing": "{letterSpacing.2}",
          "paragraphSpacing": "{paragraphSpacing.0}",
          "paragraphIndent": "{paragraphIndent.0}",
          "textCase": "{textCase.none}",
          "textDecoration": "{textDecoration.none}"
        }
      },
      "underlined": {
        "$type": "typography",
        "$value": {
          "fontFamily": "{fontFamilies.area-variable}",
          "fontWeight": "{fontWeights.area-variable-3}",
          "lineHeight": "{lineHeights.0}",
          "fontSize": "{fontSize.6}",
          "letterSpacing": "{letterSpacing.2}",
          "paragraphSpacing": "{paragraphSpacing.0}",
          "paragraphIndent": "{paragraphIndent.0}",
          "textCase": "{textCase.none}",
          "textDecoration": "{textDecoration.underline}"
        }
      },
      "strikethrough": {
        "$type": "typography",
        "$value": {
          "fontFamily": "{fontFamilies.area-variable}",
          "fontWeight": "{fontWeights.area-variable-3}",
          "lineHeight": "{lineHeights.0}",
          "fontSize": "{fontSize.6}",
          "letterSpacing": "{letterSpacing.2}",
          "paragraphSpacing": "{paragraphSpacing.0}",
          "paragraphIndent": "{paragraphIndent.0}",
          "textCase": "{textCase.none}",
          "textDecoration": "{textDecoration.line-through}"
        }
      }
    }
  },
  "text 4x large": {
    "leading-normal": {
      "regular": {
        "$type": "typography",
        "$value": {
          "fontFamily": "{fontFamilies.area-variable}",
          "fontWeight": "{fontWeights.area-variable-3}",
          "lineHeight": "{lineHeights.7}",
          "fontSize": "{fontSize.7}",
          "letterSpacing": "{letterSpacing.3}",
          "paragraphSpacing": "{paragraphSpacing.0}",
          "paragraphIndent": "{paragraphIndent.0}",
          "textCase": "{textCase.none}",
          "textDecoration": "{textDecoration.none}"
        }
      },
      "medium": {
        "$type": "typography",
        "$value": {
          "fontFamily": "{fontFamilies.area-variable}",
          "fontWeight": "{fontWeights.area-variable-3}",
          "lineHeight": "{lineHeights.7}",
          "fontSize": "{fontSize.7}",
          "letterSpacing": "{letterSpacing.3}",
          "paragraphSpacing": "{paragraphSpacing.0}",
          "paragraphIndent": "{paragraphIndent.0}",
          "textCase": "{textCase.none}",
          "textDecoration": "{textDecoration.none}"
        }
      },
      "semibold": {
        "$type": "typography",
        "$value": {
          "fontFamily": "{fontFamilies.area-variable}",
          "fontWeight": "{fontWeights.area-variable-4}",
          "lineHeight": "{lineHeights.7}",
          "fontSize": "{fontSize.7}",
          "letterSpacing": "{letterSpacing.3}",
          "paragraphSpacing": "{paragraphSpacing.0}",
          "paragraphIndent": "{paragraphIndent.0}",
          "textCase": "{textCase.none}",
          "textDecoration": "{textDecoration.none}"
        }
      },
      "bold": {
        "$type": "typography",
        "$value": {
          "fontFamily": "{fontFamilies.area-variable}",
          "fontWeight": "{fontWeights.area-variable-4}",
          "lineHeight": "{lineHeights.7}",
          "fontSize": "{fontSize.7}",
          "letterSpacing": "{letterSpacing.3}",
          "paragraphSpacing": "{paragraphSpacing.0}",
          "paragraphIndent": "{paragraphIndent.0}",
          "textCase": "{textCase.none}",
          "textDecoration": "{textDecoration.none}"
        }
      },
      "italic": {
        "$type": "typography",
        "$value": {
          "fontFamily": "{fontFamilies.area-variable}",
          "fontWeight": "{fontWeights.area-variable-5}",
          "lineHeight": "{lineHeights.7}",
          "fontSize": "{fontSize.7}",
          "letterSpacing": "{letterSpacing.3}",
          "paragraphSpacing": "{paragraphSpacing.0}",
          "paragraphIndent": "{paragraphIndent.0}",
          "textCase": "{textCase.none}",
          "textDecoration": "{textDecoration.none}"
        }
      },
      "underlined": {
        "$type": "typography",
        "$value": {
          "fontFamily": "{fontFamilies.area-variable}",
          "fontWeight": "{fontWeights.area-variable-3}",
          "lineHeight": "{lineHeights.7}",
          "fontSize": "{fontSize.7}",
          "letterSpacing": "{letterSpacing.3}",
          "paragraphSpacing": "{paragraphSpacing.0}",
          "paragraphIndent": "{paragraphIndent.0}",
          "textCase": "{textCase.none}",
          "textDecoration": "{textDecoration.underline}"
        }
      },
      "strikethrough": {
        "$type": "typography",
        "$value": {
          "fontFamily": "{fontFamilies.area-variable}",
          "fontWeight": "{fontWeights.area-variable-3}",
          "lineHeight": "{lineHeights.7}",
          "fontSize": "{fontSize.7}",
          "letterSpacing": "{letterSpacing.3}",
          "paragraphSpacing": "{paragraphSpacing.0}",
          "paragraphIndent": "{paragraphIndent.0}",
          "textCase": "{textCase.none}",
          "textDecoration": "{textDecoration.line-through}"
        }
      }
    },
    "leading-none": {
      "regular": {
        "$type": "typography",
        "$value": {
          "fontFamily": "{fontFamilies.area-variable}",
          "fontWeight": "{fontWeights.area-variable-3}",
          "lineHeight": "{lineHeights.0}",
          "fontSize": "{fontSize.7}",
          "letterSpacing": "{letterSpacing.3}",
          "paragraphSpacing": "{paragraphSpacing.0}",
          "paragraphIndent": "{paragraphIndent.0}",
          "textCase": "{textCase.none}",
          "textDecoration": "{textDecoration.none}"
        }
      },
      "medium": {
        "$type": "typography",
        "$value": {
          "fontFamily": "{fontFamilies.area-variable}",
          "fontWeight": "{fontWeights.area-variable-3}",
          "lineHeight": "{lineHeights.0}",
          "fontSize": "{fontSize.7}",
          "letterSpacing": "{letterSpacing.3}",
          "paragraphSpacing": "{paragraphSpacing.0}",
          "paragraphIndent": "{paragraphIndent.0}",
          "textCase": "{textCase.none}",
          "textDecoration": "{textDecoration.none}"
        }
      },
      "semibold": {
        "$type": "typography",
        "$value": {
          "fontFamily": "{fontFamilies.area-variable}",
          "fontWeight": "{fontWeights.area-variable-4}",
          "lineHeight": "{lineHeights.0}",
          "fontSize": "{fontSize.7}",
          "letterSpacing": "{letterSpacing.3}",
          "paragraphSpacing": "{paragraphSpacing.0}",
          "paragraphIndent": "{paragraphIndent.0}",
          "textCase": "{textCase.none}",
          "textDecoration": "{textDecoration.none}"
        }
      },
      "bold": {
        "$type": "typography",
        "$value": {
          "fontFamily": "{fontFamilies.area-variable}",
          "fontWeight": "{fontWeights.area-variable-4}",
          "lineHeight": "{lineHeights.0}",
          "fontSize": "{fontSize.7}",
          "letterSpacing": "{letterSpacing.3}",
          "paragraphSpacing": "{paragraphSpacing.0}",
          "paragraphIndent": "{paragraphIndent.0}",
          "textCase": "{textCase.none}",
          "textDecoration": "{textDecoration.none}"
        }
      },
      "italic": {
        "$type": "typography",
        "$value": {
          "fontFamily": "{fontFamilies.area-variable}",
          "fontWeight": "{fontWeights.area-variable-5}",
          "lineHeight": "{lineHeights.0}",
          "fontSize": "{fontSize.7}",
          "letterSpacing": "{letterSpacing.3}",
          "paragraphSpacing": "{paragraphSpacing.0}",
          "paragraphIndent": "{paragraphIndent.0}",
          "textCase": "{textCase.none}",
          "textDecoration": "{textDecoration.none}"
        }
      },
      "underlined": {
        "$type": "typography",
        "$value": {
          "fontFamily": "{fontFamilies.area-variable}",
          "fontWeight": "{fontWeights.area-variable-3}",
          "lineHeight": "{lineHeights.0}",
          "fontSize": "{fontSize.7}",
          "letterSpacing": "{letterSpacing.3}",
          "paragraphSpacing": "{paragraphSpacing.0}",
          "paragraphIndent": "{paragraphIndent.0}",
          "textCase": "{textCase.none}",
          "textDecoration": "{textDecoration.underline}"
        }
      },
      "strikethrough": {
        "$type": "typography",
        "$value": {
          "fontFamily": "{fontFamilies.area-variable}",
          "fontWeight": "{fontWeights.area-variable-3}",
          "lineHeight": "{lineHeights.0}",
          "fontSize": "{fontSize.7}",
          "letterSpacing": "{letterSpacing.3}",
          "paragraphSpacing": "{paragraphSpacing.0}",
          "paragraphIndent": "{paragraphIndent.0}",
          "textCase": "{textCase.none}",
          "textDecoration": "{textDecoration.line-through}"
        }
      }
    }
  },
  "text 5x large": {
    "leading-none": {
      "regular": {
        "$type": "typography",
        "$value": {
          "fontFamily": "{fontFamilies.area-variable}",
          "fontWeight": "{fontWeights.area-variable-3}",
          "lineHeight": "{lineHeights.8}",
          "fontSize": "{fontSize.8}",
          "letterSpacing": "{letterSpacing.4}",
          "paragraphSpacing": "{paragraphSpacing.0}",
          "paragraphIndent": "{paragraphIndent.0}",
          "textCase": "{textCase.none}",
          "textDecoration": "{textDecoration.none}"
        }
      },
      "medium": {
        "$type": "typography",
        "$value": {
          "fontFamily": "{fontFamilies.area-variable}",
          "fontWeight": "{fontWeights.area-variable-3}",
          "lineHeight": "{lineHeights.8}",
          "fontSize": "{fontSize.8}",
          "letterSpacing": "{letterSpacing.4}",
          "paragraphSpacing": "{paragraphSpacing.0}",
          "paragraphIndent": "{paragraphIndent.0}",
          "textCase": "{textCase.none}",
          "textDecoration": "{textDecoration.none}"
        }
      },
      "semibold": {
        "$type": "typography",
        "$value": {
          "fontFamily": "{fontFamilies.area-variable}",
          "fontWeight": "{fontWeights.area-variable-4}",
          "lineHeight": "{lineHeights.8}",
          "fontSize": "{fontSize.8}",
          "letterSpacing": "{letterSpacing.4}",
          "paragraphSpacing": "{paragraphSpacing.0}",
          "paragraphIndent": "{paragraphIndent.0}",
          "textCase": "{textCase.none}",
          "textDecoration": "{textDecoration.none}"
        }
      },
      "bold": {
        "$type": "typography",
        "$value": {
          "fontFamily": "{fontFamilies.area-variable}",
          "fontWeight": "{fontWeights.area-variable-4}",
          "lineHeight": "{lineHeights.8}",
          "fontSize": "{fontSize.8}",
          "letterSpacing": "{letterSpacing.4}",
          "paragraphSpacing": "{paragraphSpacing.0}",
          "paragraphIndent": "{paragraphIndent.0}",
          "textCase": "{textCase.none}",
          "textDecoration": "{textDecoration.none}"
        }
      },
      "italic": {
        "$type": "typography",
        "$value": {
          "fontFamily": "{fontFamilies.area-variable}",
          "fontWeight": "{fontWeights.area-variable-5}",
          "lineHeight": "{lineHeights.8}",
          "fontSize": "{fontSize.8}",
          "letterSpacing": "{letterSpacing.4}",
          "paragraphSpacing": "{paragraphSpacing.0}",
          "paragraphIndent": "{paragraphIndent.0}",
          "textCase": "{textCase.none}",
          "textDecoration": "{textDecoration.none}"
        }
      },
      "underlined": {
        "$type": "typography",
        "$value": {
          "fontFamily": "{fontFamilies.area-variable}",
          "fontWeight": "{fontWeights.area-variable-3}",
          "lineHeight": "{lineHeights.8}",
          "fontSize": "{fontSize.8}",
          "letterSpacing": "{letterSpacing.4}",
          "paragraphSpacing": "{paragraphSpacing.0}",
          "paragraphIndent": "{paragraphIndent.0}",
          "textCase": "{textCase.none}",
          "textDecoration": "{textDecoration.underline}"
        }
      },
      "strikethrough": {
        "$type": "typography",
        "$value": {
          "fontFamily": "{fontFamilies.area-variable}",
          "fontWeight": "{fontWeights.area-variable-3}",
          "lineHeight": "{lineHeights.8}",
          "fontSize": "{fontSize.8}",
          "letterSpacing": "{letterSpacing.4}",
          "paragraphSpacing": "{paragraphSpacing.0}",
          "paragraphIndent": "{paragraphIndent.0}",
          "textCase": "{textCase.none}",
          "textDecoration": "{textDecoration.line-through}"
        }
      }
    }
  },
  "textCase": {
    "none": {
      "$type": "textCase",
      "$value": "none"
    }
  },
  "textDecoration": {
    "none": {
      "$type": "textDecoration",
      "$value": "none"
    },
    "underline": {
      "$type": "textDecoration",
      "$value": "underline"
    },
    "line-through": {
      "$type": "textDecoration",
      "$value": "line-through"
    }
  },
  "paragraphIndent": {
    "0": {
      "$type": "dimension",
      "$value": "0px"
    }
  }
}